release_check/__init__.py
release_check/cli.py
release_check/constants.py
release_check/log.py
release_check/utils.py
release_check/subcmd/__init__.py
release_check/subcmd/batch.py
release_check/subcmd/docker.py
release_check/subcmd/single.py
dcs_release_check-0.0.7.dist-info/METADATA
dcs_release_check-0.0.7.dist-info/WHEEL
dcs_release_check-0.0.7.dist-info/entry_points.txt
dcs_release_check-0.0.7.dist-info/top_level.txt
dcs_release_check-0.0.7.dist-info/RECORD
