Metadata-Version: 2.1
Name: dcs-release-check
Version: 0.0.7
Summary: "Tool to query latest versions from source code hosting platforms such as GitHub."
Home-page: UNKNOWN
Author: "Fabian Mueller"
Author-email: "packages@dotcs.me"
License: UNKNOWN
Platform: UNKNOWN
Classifier: Development Status :: 3 - Alpha
Classifier: Environment :: Console
Classifier: Programming Language :: Python :: 3
Classifier: Programming Language :: Python :: 3.8
Classifier: Operating System :: OS Independent
Classifier: Natural Language :: English
Requires-Dist: beautifulsoup4
Requires-Dist: docker
Requires-Dist: packaging
Requires-Dist: python-dateutil
Requires-Dist: requests
Requires-Dist: tabulate
Requires-Dist: toml
Provides-Extra: develop
Requires-Dist: black ; extra == 'develop'
Requires-Dist: pep517 ; extra == 'develop'
Requires-Dist: twine ; extra == 'develop'
